agatta/__init__.py
agatta/__version__.py
agatta/agatta.png
agatta/analysis.py
agatta/ini.py
agatta/interpret.py
agatta/main.py
agatta/out.py
agatta/search.py
agatta-0.9.6.dist-info/licenses/AUTHORS
agatta-0.9.6.dist-info/licenses/LICENSE
agatta-0.9.6.dist-info/METADATA
agatta-0.9.6.dist-info/WHEEL
agatta-0.9.6.dist-info/entry_points.txt
agatta-0.9.6.dist-info/top_level.txt
agatta-0.9.6.dist-info/RECORD
