Metadata-Version: 2.4
Name: Agatta
Version: 0.9.6
Summary: Three-item analysis python package
Home-page: https://github.com/vrineau/Agatta
Author: Valentin Rineau
Author-email: valentin.rineau@sorbonne-universite.fr
License: GNU General Public License v3.0+
Classifier: Development Status :: 4 - Beta
Classifier: License :: OSI Approved :: GNU General Public License v3 (GPLv3)
Classifier: Operating System :: Microsoft :: Windows
Classifier: Operating System :: MacOS
Classifier: Operating System :: POSIX :: Linux
Classifier: Programming Language :: Python :: 3
Classifier: Intended Audience :: Science/Research
Classifier: Intended Audience :: Education
Classifier: Intended Audience :: Other Audience
Classifier: Natural Language :: English
Classifier: Topic :: Scientific/Engineering
Classifier: Topic :: Scientific/Engineering :: Bio-Informatics
Classifier: Topic :: Scientific/Engineering :: Visualization
Requires-Python: >=3.8.0
License-File: LICENSE
License-File: AUTHORS
Requires-Dist: docopt==0.6.2
Requires-Dist: ete3==3.1.3
Requires-Dist: tqdm==4.66.3
Requires-Dist: treeswift==1.1.37
Requires-Dist: six==1.16.0
Requires-Dist: numpy==1.24.4
Requires-Dist: pandas==2.2.3
Requires-Dist: pypdf==3.17.0
Dynamic: author
Dynamic: author-email
Dynamic: classifier
Dynamic: description
Dynamic: description-content-type
Dynamic: home-page
Dynamic: license
Dynamic: license-file
Dynamic: requires-dist
Dynamic: requires-python
Dynamic: summary
